{
  "$schema": "http://interagent.github.io/interagent-hyper-schema",
  "type": [
    "object"
  ],
  "definitions": {
    "app": {
      "$schema": "http://json-schema.org/draft-04/hyper-schema",
      "title": "FIXME - App",
      "description": "FIXME",
      "stability": "prototype",
      "strictProperties": true,
      "type": [
        "object"
      ],
      "definitions": {
        "id": {
          "description": "unique identifier of app",
          "readOnly": true,
          "format": "uuid",
          "type": [
            "string"
          ]
        },
        "name": {
          "description": "unique name of app",
          "readOnly": true,
          "type": [
            "string"
          ]
        },
        "identity": {
          "anyOf": [
            {
              "$ref": "#/definitions/app/definitions/id"
            },
            {
              "$ref": "#/definitions/app/definitions/name"
            }
          ]
        },
        "created_at": {
          "description": "when app was created",
          "format": "date-time",
          "type": [
            "string"
          ]
        },
        "updated_at": {
          "description": "when app was updated",
          "format": "date-time",
          "type": [
            "string"
          ]
        }
      },
      "links": [
        {
          "description": "Create a new app.",
          "href": "/apps",
          "method": "POST",
          "rel": "create",
          "schema": {
            "properties": {
            },
            "type": [
              "object"
            ]
          },
          "title": "Create"
        },
        {
          "description": "Delete an existing app.",
          "href": "/apps/{(%23%2Fdefinitions%2Fapp%2Fdefinitions%2Fidentity)}",
          "method": "DELETE",
          "rel": "destroy",
          "title": "Delete"
        },
        {
          "description": "Info for existing app.",
          "href": "/apps/{(%23%2Fdefinitions%2Fapp%2Fdefinitions%2Fidentity)}",
          "method": "GET",
          "rel": "self",
          "title": "Info"
        },
        {
          "description": "List existing apps.",
          "href": "/apps",
          "method": "GET",
          "rel": "instances",
          "title": "List"
        },
        {
          "description": "Update an existing app.",
          "href": "/apps/{(%23%2Fdefinitions%2Fapp%2Fdefinitions%2Fidentity)}",
          "method": "PATCH",
          "rel": "update",
          "schema": {
            "properties": {
            },
            "type": [
              "object"
            ]
          },
          "title": "Update"
        }
      ],
      "properties": {
        "created_at": {
          "$ref": "#/definitions/app/definitions/created_at"
        },
        "id": {
          "$ref": "#/definitions/app/definitions/id"
        },
        "name": {
          "$ref": "#/definitions/app/definitions/name"
        },
        "updated_at": {
          "$ref": "#/definitions/app/definitions/updated_at"
        }
      }
    },
    "user": {
      "$schema": "http://json-schema.org/draft-04/hyper-schema",
      "title": "FIXME - User",
      "description": "FIXME",
      "stability": "prototype",
      "strictProperties": true,
      "type": [
        "object"
      ],
      "definitions": {
        "id": {
          "description": "unique identifier of user",
          "readOnly": true,
          "format": "uuid",
          "type": [
            "string"
          ]
        },
        "name": {
          "description": "unique name of user",
          "readOnly": true,
          "type": [
            "string"
          ]
        },
        "identity": {
          "anyOf": [
            {
              "$ref": "#/definitions/user/definitions/id"
            },
            {
              "$ref": "#/definitions/user/definitions/name"
            }
          ]
        },
        "created_at": {
          "description": "when user was created",
          "format": "date-time",
          "type": [
            "string"
          ]
        },
        "updated_at": {
          "description": "when user was updated",
          "format": "date-time",
          "type": [
            "string"
          ]
        }
      },
      "links": [
        {
          "description": "Create a new user.",
          "href": "/users",
          "method": "POST",
          "rel": "create",
          "schema": {
            "properties": {
            },
            "type": [
              "object"
            ]
          },
          "title": "Create"
        },
        {
          "description": "Delete an existing user.",
          "href": "/users/{(%23%2Fdefinitions%2Fuser%2Fdefinitions%2Fidentity)}",
          "method": "DELETE",
          "rel": "destroy",
          "title": "Delete"
        },
        {
          "description": "Info for existing user.",
          "href": "/users/{(%23%2Fdefinitions%2Fuser%2Fdefinitions%2Fidentity)}",
          "method": "GET",
          "rel": "self",
          "title": "Info"
        },
        {
          "description": "List existing users.",
          "href": "/users",
          "method": "GET",
          "rel": "instances",
          "title": "List"
        },
        {
          "description": "Update an existing user.",
          "href": "/users/{(%23%2Fdefinitions%2Fuser%2Fdefinitions%2Fidentity)}",
          "method": "PATCH",
          "rel": "update",
          "schema": {
            "properties": {
            },
            "type": [
              "object"
            ]
          },
          "title": "Update"
        }
      ],
      "properties": {
        "created_at": {
          "$ref": "#/definitions/user/definitions/created_at"
        },
        "id": {
          "$ref": "#/definitions/user/definitions/id"
        },
        "name": {
          "$ref": "#/definitions/user/definitions/name"
        },
        "updated_at": {
          "$ref": "#/definitions/user/definitions/updated_at"
        }
      }
    }
  },
  "properties": {
    "app": {
      "$ref": "#/definitions/app"
    },
    "user": {
      "$ref": "#/definitions/user"
    }
  },
  "description": "Hello world prmd API",
  "id": "hello-prmd",
  "links": [
    {
      "href": "https://api.hello.com",
      "rel": "self"
    }
  ],
  "title": "Hello Prmd"
}
